{
	"healthchecks": [
		{
			"token": "site",
			"description": "My web site",
			"ranges": [
				5000,
				10000
			]
		},
		{
			"token": "pcoutinho1",
			"description": "Paulo Coutinho blog",
			"ranges": [
				5000,
				10000
			]
		},
		{
			"token": "pcoutinho2",
			"description": "Paulo Coutinho blog",
			"ranges": [
				5000,
				10000
			]
		},
		{
			"token": "pcoutinho3",
			"description": "Paulo Coutinho blog",
			"ranges": [
				5000,
				10000
			]
		},
		{
			"token": "pcoutinho4",
			"description": "Paulo Coutinho blog",
			"ranges": [
				5000,
				10000
			]
		},
		{
			"token": "pcoutinho5",
			"description": "Paulo Coutinho blog",
			"ranges": [
				5000,
				10000
			]
		},
		{
			"token": "pcoutinho6",
			"description": "Paulo Coutinho blog",
			"ranges": [
				5000,
				10000
			]
		},
		{
			"token": "pcoutinho7",
			"description": "Paulo Coutinho blog",
			"ranges": [
				5000,
				10000
			]
		},
		{
			"token": "pcoutinho8",
			"description": "Paulo Coutinho blog",
			"ranges": [
				5000,
				10000
			]
		},
		{
			"token": "pcoutinho9",
			"description": "Paulo Coutinho blog",
			"ranges": [
				5000,
				10000
			]
		},
		{
			"token": "pcoutinho10",
			"description": "Paulo Coutinho blog",
			"ranges": [
				5000,
				10000
			]
		},
		{
			"token": "pcoutinho11",
			"description": "Paulo Coutinho blog",
			"ranges": [
				5000,
				10000
			]
		},
		{
			"token": "pcoutinho12",
			"description": "Paulo Coutinho blog",
			"ranges": [
				5000,
				10000
			]
		},
		{
			"token": "pcoutinho13",
			"description": "Paulo Coutinho blog",
			"ranges": [
				5000,
				10000
			]
		},
		{
			"token": "pcoutinho14",
			"description": "Paulo Coutinho blog",
			"ranges": [
				5000,
				10000
			]
		},
		{
			"token": "pcoutinho15",
			"description": "Paulo Coutinho blog",
			"ranges": [
				5000,
				10000
			]
		},
		{
			"token": "pcoutinho16",
			"description": "Paulo Coutinho blog",
			"ranges": [
				5000,
				10000
			]
		},
		{
			"token": "pcoutinho17",
			"description": "Paulo Coutinho blog",
			"ranges": [
				5000,
				10000
			]
		},
		{
			"token": "pcoutinho18",
			"description": "Paulo Coutinho blog",
			"ranges": [
				5000,
				10000
			]
		},
		{
			"token": "pcoutinho19",
			"description": "Paulo Coutinho blog",
			"ranges": [
				5000,
				10000
			]
		},
		{
			"token": "pcoutinho20",
			"description": "Paulo Coutinho blog",
			"ranges": [
				5000,
				10000
			]
		},
		{
			"token": "pcoutinho21",
			"description": "Paulo Coutinho blog",
			"ranges": [
				5000,
				10000
			]
		},
		{
			"token": "pcoutinho22",
			"description": "Paulo Coutinho blog",
			"ranges": [
				5000,
				10000
			]
		},
		{
			"token": "pcoutinho23",
			"description": "Paulo Coutinho blog",
			"ranges": [
				5000,
				10000
			]
		},
		{
			"token": "pcoutinho24",
			"description": "Paulo Coutinho blog",
			"ranges": [
				5000,
				10000
			]
		},
		{
			"token": "pcoutinho25",
			"description": "Paulo Coutinho blog",
			"ranges": [
				5000,
				10000
			]
		},
		{
			"token": "pcoutinho26",
			"description": "Paulo Coutinho blog",
			"ranges": [
				5000,
				10000
			]
		},
		{
			"token": "pcoutinho27",
			"description": "Paulo Coutinho blog",
			"ranges": [
				5000,
				10000
			]
		},
		{
			"token": "pcoutinho28",
			"description": "Paulo Coutinho blog",
			"ranges": [
				5000,
				10000
			]
		},
		{
			"token": "pcoutinho29",
			"description": "Paulo Coutinho blog",
			"ranges": [
				5000,
				10000
			]
		},
		{
			"token": "pcoutinho30",
			"description": "Paulo Coutinho blog",
			"ranges": [
				5000,
				10000
			]
		},
		{
			"token": "pcoutinho31",
			"description": "Paulo Coutinho blog",
			"ranges": [
				5000,
				10000
			]
		},
		{
			"token": "pcoutinho32",
			"description": "Paulo Coutinho blog",
			"ranges": [
				5000,
				10000
			]
		},
		{
			"token": "pcoutinho33",
			"description": "Paulo Coutinho blog",
			"ranges": [
				5000,
				10000
			]
		},
		{
			"token": "pcoutinho34",
			"description": "Paulo Coutinho blog",
			"ranges": [
				5000,
				10000
			]
		},
		{
			"token": "pcoutinho35",
			"description": "Paulo Coutinho blog",
			"ranges": [
				5000,
				10000
			]
		},
		{
			"token": "pcoutinho36",
			"description": "Paulo Coutinho blog",
			"ranges": [
				5000,
				10000
			]
		},
		{
			"token": "prsolucoes37",
			"description": "PRSoluções web site",
			"ranges": [
				5000,
				10000
			]
		},
		{
			"token": "prsolucoes38",
			"description": "PRSoluções web site",
			"ranges": [
				5000,
				10000
			]
		},
		{
			"token": "prsolucoes39",
			"description": "PRSoluções web site",
			"ranges": [
				5000,
				10000
			]
		},
		{
			"token": "prsolucoes40",
			"description": "PRSoluções web site",
			"ranges": [
				5000,
				10000
			]
		}
	]
}